{
    "@class": "com.kony.gen.viz.model.component.KVizUserWidget",
    "DNDConfig": null,
    "__markedForDelete__": true,
    "__parentReadjusting__": false,
    "_bottom_": {
        "type": "string",
        "value": "0dp"
    },
    "_children_": [],
    "_height_": "10%",
    "_left_": {
        "type": "string",
        "value": "0dp"
    },
    "_margin_": [
        0,
        0,
        0,
        0
    ],
    "_orientation_": 1,
    "_padding_": [
        0,
        0,
        0,
        0
    ],
    "_percent_": true,
    "_render_": true,
    "_right_": {
        "type": "string",
        "value": "0dp"
    },
    "_skin_": "sf315405b5004a77bff02788ca62a1bf",
    "_top_": {
        "type": "string",
        "value": "90%"
    },
    "_width_": "100%",
    "areflexpropsreferenced": false,
    "autogrowmode": 0,
    "canUpdateUI": true,
    "clipbounds": true,
    "containerweight": 0,
    "dataDiffs": {
        "componentBottomBar": {
            "__events__": {},
            "__info__": {
                "isRoot": true,
                "kuid": "b5ddd93f14144be3b278b0a1ca0b0a07",
                "srcKUID": "ed8c9eb96d7349d68141edb0c49cff2a",
                "wType": "FlexContainer"
            },
            "bottom": {
                "type": "string",
                "value": "0dp"
            },
            "left": {
                "type": "string",
                "value": "0dp"
            },
            "right": {
                "type": "string",
                "value": "0dp"
            },
            "top": {
                "type": "string",
                "value": "90%"
            },
            "zIndex": 1
        },
        "flxSuperAdd": {
            "__events__": {},
            "__info__": {
                "kuid": "fae2391ab80346998e50e7adaa9ed1e7",
                "srcKUID": "cbd27bf8813e44899de2a39cc770d144",
                "wType": "FlexContainer"
            }
        },
        "flxSuperHistory": {
            "__events__": {},
            "__info__": {
                "kuid": "i9169371dc7c463c802f9e21496ac181",
                "srcKUID": "b2a2216a59c84c089b76d3c1bd585cfd",
                "wType": "FlexContainer"
            }
        },
        "flxSuperShopping": {
            "__events__": {},
            "__info__": {
                "kuid": "fecd75e4a7c44c8095a59e3e77895ded",
                "srcKUID": "cfa77b6304734c9787f4082e05bb1321",
                "wType": "FlexContainer"
            }
        },
        "flxSuperUser": {
            "__events__": {},
            "__info__": {
                "kuid": "c5ac4c07c8e146d584fec69d7369028e",
                "srcKUID": "bd602b0d65164c72bbfd010aaa0c3363",
                "wType": "FlexContainer"
            }
        },
        "imgAddPost": {
            "__events__": {},
            "__info__": {
                "kuid": "df82afb2ba3148d4be89ec4c98209826",
                "srcKUID": "d69c23dd4ecd451e80e5faf999772af8",
                "wType": "Image"
            }
        },
        "imgHistory": {
            "__events__": {},
            "__info__": {
                "kuid": "j172db84656d4955bad70f1b7dbd66bf",
                "srcKUID": "c2bc9b9c5037432f8d7aeb988c43ee32",
                "wType": "Image"
            }
        },
        "imgProducts": {
            "__events__": {},
            "__info__": {
                "kuid": "h9a3c33bd2884e269a2066b7ad2ebc5d",
                "srcKUID": "ja97ee1c97f04d7eaee04114c99798e4",
                "wType": "Image"
            }
        },
        "imgUser": {
            "__events__": {},
            "__info__": {
                "kuid": "ffaf3cfa1cd04b79bbf9b064681a723b",
                "srcKUID": "ed2cdc3082a24b5cbaad06a1aa0a0f61",
                "wType": "Image"
            }
        }
    },
    "id": "componentBottomBar",
    "info": null,
    "isdatareferenced": false,
    "isvisible": true,
    "kuid": "b899b58687764cf3ba43c5ae901a3620",
    "layouttype": 3,
    "masterType": 0,
    "name": "kony.ui.UserWidgetInstance",
    "parent": "frmProductDescription",
    "pf": "frmProductDescription",
    "snaptogrid": true,
    "sourceUserWidget": "ed8c9eb96d7349d68141edb0c49cff2a",
    "wType": "UserWidgetInstance",
    "zindex": 1
}